{
  "summary": "Client (alex) requested that helloworld be changed to output \"testing 123\"; the developer executed change request req_1760977803402 and updated helloworld.py. Architect, PM, and QA did not provide comments or reviews during this change.",
  "decisions": [
    {
      "title": "Change request executed",
      "details": "Client requested change to helloworld output; developer executed change request req_1760977803402 and updated helloworld.py to output 'testing 123'.",
      "refs": []
    }
  ],
  "sign_offs": [
    {
      "who": "DEVELOPER",
      "what": "Executed change request req_1760977803402 and updated helloworld.py",
      "timestamp": "2025-10-20 12:00:00"
    }
  ],
  "actions": [
    {
      "owner": "DEVELOPER",
      "task": "Execute requested change to helloworld.py to output 'testing 123' (req_1760977803402)",
      "due": ""
    },
    {
      "owner": "QA",
      "task": "Perform verification and regression tests on updated helloworld.py to confirm output and absence of regressions",
      "due": ""
    }
  ],
  "backlog_deltas": [
    {
      "type": "update",
      "id": "req_1760977803402",
      "title": "Update helloworld.py to output 'testing 123'"
    }
  ],
  "risks": [
    {
      "risk": "Change deployed without explicit review from Architect, PM, or QA which may introduce regressions or missed requirements.",
      "mitigation": "Schedule quick post-deploy review and run QA regression tests; revert or patch if issues are found."
    }
  ],
  "participants": null
}